src/inductive_logic_programming/__init__.py
src/inductive_logic_programming/foil.py
src/inductive_logic_programming/foil_algorithm_variants.py
src/inductive_logic_programming/foil_comprehensive_config.py
src/inductive_logic_programming/foil_quinlan1990_implementation.py
src/inductive_logic_programming/foil_research_accurate.py
src/inductive_logic_programming/ilp_core.py
src/inductive_logic_programming/progol.py
src/inductive_logic_programming/progol_comprehensive_config.py
src/inductive_logic_programming/rule_refinement.py
src/inductive_logic_programming/ilp_modules/__init__.py
src/inductive_logic_programming/ilp_modules/coverage_analysis.py
src/inductive_logic_programming/ilp_modules/foil_progol_implementation.py
src/inductive_logic_programming/ilp_modules/hypothesis_generation.py
src/inductive_logic_programming/ilp_modules/ilp_config.py
src/inductive_logic_programming/ilp_modules/logical_structures.py
src/inductive_logic_programming/ilp_modules/predicate_system.py
src/inductive_logic_programming/ilp_modules/rule_refinement.py
src/inductive_logic_programming/ilp_modules/semantic_evaluation.py
src/inductive_logic_programming/ilp_modules/unification_engine.py
src/inductive_logic_programming/old_archive/predicate_system_original_1182_lines.py
src/inductive_logic_programming/predicate_modules/__init__.py
src/inductive_logic_programming/predicate_modules/predicate_core.py
inductive_logic_programming-1.2.2.dist-info/METADATA
inductive_logic_programming-1.2.2.dist-info/WHEEL
inductive_logic_programming-1.2.2.dist-info/licenses/LICENSE
inductive_logic_programming-1.2.2.dist-info/RECORD
